Metadata-Version: 2.4
Name: tap-jira
Version: 2.6.0
Summary: Singer.io tap for extracting data from the Jira API
Home-page: http://singer.io
Author: Stitch
Classifier: Programming Language :: Python :: 3 :: Only
License-File: LICENSE
Requires-Dist: singer-python==6.0.1
Requires-Dist: requests==2.32.4
Requires-Dist: dateparser
Provides-Extra: dev
Requires-Dist: pylint; extra == "dev"
Requires-Dist: nose2; extra == "dev"
Requires-Dist: ipdb; extra == "dev"
Dynamic: author
Dynamic: classifier
Dynamic: home-page
Dynamic: license-file
Dynamic: provides-extra
Dynamic: requires-dist
Dynamic: summary
